pyparts/__init__.py
pyparts/logic/__init__.py
pyparts/logic/pid_controller.py
pyparts/parts/__init__.py
pyparts/parts/base_part.py
pyparts/parts/display/__init__.py
pyparts/parts/display/screen/__init__.py
pyparts/parts/display/screen/nokia5110.py
pyparts/parts/encoder/__init__.py
pyparts/parts/encoder/rotary_encoder.py
pyparts/parts/led/__init__.py
pyparts/parts/led/rgb_led.py
pyparts/parts/sensor/__init__.py
pyparts/parts/sensor/temperature/__init__.py
pyparts/parts/sensor/temperature/base_temperature_sensor.py
pyparts/parts/sensor/temperature/max31855.py
pyparts/parts/switch/__init__.py
pyparts/parts/switch/button.py
pyparts/platforms/__init__.py
pyparts/platforms/base_platform.py
pyparts/platforms/raspberrypi_platform.py
pyparts/platforms/gpio/__init__.py
pyparts/platforms/gpio/base_gpio.py
pyparts/platforms/gpio/raspberrypi_gpio.py
pyparts/platforms/pwm/__init__.py
pyparts/platforms/pwm/base_pwm.py
pyparts/platforms/pwm/raspberrypi_pwm.py
pyparts/platforms/spi/__init__.py
pyparts/platforms/spi/base_spi.py
pyparts/platforms/spi/raspberrypi_spi.py
pyparts/systems/__init__.py
pyparts/systems/temperature_controller.py
python_pyparts-1.0.0.dist-info/DESCRIPTION.rst
python_pyparts-1.0.0.dist-info/METADATA
python_pyparts-1.0.0.dist-info/RECORD
python_pyparts-1.0.0.dist-info/WHEEL
python_pyparts-1.0.0.dist-info/metadata.json
python_pyparts-1.0.0.dist-info/top_level.txt
