Metadata-Version: 2.0
Name: python-pyparts
Version: 1.0.0
Summary: A cross platform library for embedded hardware development using single board computers.
Home-page: https://gitlab.com/seanwatson/pyparts
Author: Sean Watson
Author-email: sean@seanwatson.io
License: MIT
Keywords: raspberrypi beagleboard pine64 mbed embedded hardware gpio spi pwm electronics
Platform: UNKNOWN
Classifier: Development Status :: 3 - Alpha
Classifier: Intended Audience :: Developers
Classifier: Natural Language :: English
Classifier: License :: OSI Approved :: MIT License
Classifier: Programming Language :: Python
Classifier: Topic :: Software Development :: Libraries :: Python Modules
Requires-Dist: RPi.GPIO
Requires-Dist: spidev
